setup.cfg
setup.py
benri/__init__.py
benri.client.egg-info/PKG-INFO
benri.client.egg-info/SOURCES.txt
benri.client.egg-info/dependency_links.txt
benri.client.egg-info/namespace_packages.txt
benri.client.egg-info/not-zip-safe
benri.client.egg-info/requires.txt
benri.client.egg-info/top_level.txt
benri/client/__init__.py
benri/client/client.py