Metadata-Version: 1.0
Name: benri.client
Version: 0.0.3
Summary: A client package for benri-based services.
Home-page: http://pypi.python.org/pypi/benri.client/
Author: Mikael Hoegqvist
Author-email: hoegqvist@zib.de
License: Apache 2.0
Platform: UNKNOWN
Classifier: Development Status :: 4 - Beta
Classifier: Environment :: Web Environment
Classifier: Programming Language :: Python
Classifier: Topic :: Internet :: WWW/HTTP
Classifier: Topic :: Software Development :: Libraries
